{
    "formation": {
        "title": "Formation Deep Learning",
        "image": "https://cdn.futura-sciences.com/cdn-cgi/image/width=1920,quality=50,format=auto/sources/Deep_Learning_cc_VIGE.co_-_Fotolia.com.jpg",
        "duration": {
            "days": 3,
            "hours": 21
        },
        "target": {
            "title": "Public visé",
            "audience": [
                "Ingénieurs",
                "Data Scientists",
                "Développeurs",
                "Toute personne souhaitant approfondir ses connaissances en réseaux de neurones et apprentissage profond"
            ]
        },
        "prerequisites": {
            "title": "Prérequis",
            "requirements": [
                "Connaissances de base en programmation Python",
                "Notions en Machine Learning recommandées"
            ]
        },
        "objectives": {
            "title": "Objectifs de la formation",
            "goals": [
                "Comprendre les concepts fondamentaux du Deep Learning",
                "Maîtriser les différentes architectures de réseaux de neurones",
                "Savoir implémenter des modèles de Deep Learning avec des frameworks tels que TensorFlow ou Keras",
                "Appliquer le Deep Learning à des cas concrets tels que la vision par ordinateur et le traitement du langage naturel"
            ]
        },
        "program": {
            "title": "Programme détaillé",
            "modules": [
                {
                    "title": "Introduction au Deep Learning",
                    "topics": [
                        "Historique et évolution",
                        "Différences entre Machine Learning et Deep Learning",
                        "Applications et cas d'usage"
                    ]
                },
                {
                    "title": "Fondamentaux des réseaux de neurones",
                    "topics": [
                        "Neurone artificiel et fonction d'activation",
                        "Architecture des réseaux : couches, neurones, connexions",
                        "Propagation avant et rétropropagation de l'erreur"
                    ]
                },
                {
                    "title": "Entraînement des réseaux de neurones",
                    "topics": [
                        "Fonctions de coût et optimisation",
                        "Techniques de régularisation : dropout, batch normalization",
                        "Gestion du surapprentissage et validation croisée"
                    ]
                },
                {
                    "title": "Architectures avancées de réseaux de neurones",
                    "topics": [
                        "Réseaux de neurones convolutifs (CNN) pour la vision par ordinateur",
                        "Réseaux de neurones récurrents (RNN) et LSTM pour le traitement du langage naturel",
                        "Auto-encodeurs et réseaux antagonistes génératifs (GAN)"
                    ]
                },
                {
                    "title": "Outils et frameworks de Deep Learning",
                    "topics": [
                        "Présentation de TensorFlow et Keras",
                        "Prise en main des environnements de développement",
                        "Implémentation de modèles simples"
                    ]
                },
                {
                    "title": "Applications pratiques du Deep Learning",
                    "topics": [
                        "Classification d'images",
                        "Reconnaissance vocale",
                        "Analyse de sentiments"
                    ]
                },
                {
                    "title": "Déploiement et mise en production des modèles",
                    "topics": [
                        "Optimisation des performances",
                        "Exportation et intégration dans des applications",
                        "Surveillance et maintenance des modèles en production"
                    ]
                }
            ]
        },
        "practical": {
            "title": "Dates – lieu - Tarifs",
            "location": "À distance ou sur site",
            "price": "2 280 HT",
            "details": [
                "Sessions disponibles en distanciel",
                "Consultez notre calendrier pour les prochaines dates",
                "Tarif : 2 280 € HT"
            ]
        },
        "registration": {
            "title": "Inscription",
            "methods": [
                "Contactez-nous via notre formulaire en ligne",
                "Par téléphone au [numéro de contact]"
            ]
        }
    }
}
